LICENSE.txt
README.md
setup.py
gregium/__init__.py
gregium.egg-info/PKG-INFO
gregium.egg-info/SOURCES.txt
gregium.egg-info/dependency_links.txt
gregium.egg-info/requires.txt
gregium.egg-info/top_level.txt
gregium/buttons/__init__.py
gregium/camera/__init__.py
gregium/commandSystem/__init__.py
gregium/env/__init__.py
gregium/gamblecore/__init__.py
gregium/imports/__init__.py
gregium/old/CHANGELOG.md
gregium/old/README.md
gregium/old/__init__.py
gregium/old/gregium.png
gregium/old/gregiumAnim.png
gregium/old/gregiumAnimHD.png
gregium/old/gregiumHD.png
gregium/old/editor/SpaceMono-Bold.ttf
gregium/old/editor/SpaceMono-BoldItalic.ttf
gregium/old/editor/SpaceMono-Italic.ttf
gregium/old/editor/SpaceMono-Regular.ttf
gregium/old/editor/__init__.py
gregium/old/editor/editor.grg
gregium/old/env/__init__.py
gregium/old/gv/__init__.py
gregium/old/setup/__init__.py
gregium/old/setup/exampleFile.py
gregium/terminalLogging/__init__.py