Metadata-Version: 2.1
Name: gregium
Version: 0.1.10
Summary: A simple package with easy features for using pygame
Home-page: https://github.com/LavaTigerUnicrn/Gregium
Author: LavaTigerUnicrn
Author-email: nolanlance711@gmail.com
Project-URL: github, https://github.com/LavaTigerUnicrn/Gregium
Project-URL: issues, https://github.com/LavaTigerUnicrn/Gregium/issues
Classifier: Development Status :: 3 - Alpha
Classifier: Intended Audience :: Developers
Classifier: Topic :: Software Development :: Build Tools
Classifier: License :: OSI Approved :: MIT License
Classifier: Programming Language :: Python :: 3
License-File: LICENSE.txt
Requires-Dist: pygame-ce
Requires-Dist: pynput
Requires-Dist: pyglet
Requires-Dist: colorama
